{
 "note": "사이트 갱신 이벤트 피드 — 일일 전략 탐색 잡과 수동 작업이 한 줄씩 남긴다. 홈 하단 '최근 업데이트'와 각 페이지 배지에 표시된다. 방문자에게 의미 있는 변화만 기록(내부 리팩터링·버그수정 제외).",
 "schema": "events[] = {dt: YYYY-MM-DD, target: rotation|explorer|archive|stocks|regime|sentiment|holdings, title: 한 줄 요약}",
 "updated": "2026-07-22",
 "events": [
  {
   "dt": "2026-07-22",
   "target": "stocks",
   "title": "펀더멘털 스크리닝 — 적합도 높은 순으로 정렬·순위 표시, 화면과 DB 판정 일치"
  },
  {
   "dt": "2026-07-22",
   "target": "stocks",
   "title": "종목 시그널 고지 문구 축약 — 핵심 한 줄만 남기고 근거·한계는 접기"
  },
  {
   "dt": "2026-07-22",
   "target": "stocks",
   "title": "누적 스토어 확장 — 전략 풀·성과·구성·유니버스·스크리닝 이력을 DB에 정리"
  },
  {
   "dt": "2026-07-22",
   "target": "stocks",
   "title": "스크리닝 항목마다 뜻·판정 기준을 목록 위에 상시 표시(골든 임박·과밀숏·눌림목 등 16종)"
  },
  {
   "dt": "2026-07-22",
   "target": "stocks",
   "title": "펀더멘털 스크리닝 6종 신설 — 저평가 우량주·성장주·배당 인컴·현금창출력·GARP·저변동 방어"
  },
  {
   "dt": "2026-07-22",
   "target": "archive",
   "title": "기각 아카이브 41번째 등재 — 강세추세 과매도 스냅백(선행 타점)"
  },
  {
   "dt": "2026-07-21",
   "target": "rotation",
   "title": "전략 풀 63 → 71종 — 미국 지수 밖 8종(글로벌·채권·통화·대체) 추가"
  },
  {
   "dt": "2026-07-21",
   "target": "explorer",
   "title": "22개 전략에 '어떤 상황에서 쓰나'(유리·불리·결합) 추가"
  },
  {
   "dt": "2026-07-21",
   "target": "explorer",
   "title": "기간별 성과 표(3M·6M·YTD·1Y·3Y) + SPX·NDX 총수익 이중 벤치마크"
  },
  {
   "dt": "2026-07-21",
   "target": "explorer",
   "title": "전략별 현재 포트폴리오 구성(종목·비중) 공개"
  },
  {
   "dt": "2026-07-21",
   "target": "stocks",
   "title": "종목별 '왜 이 신호인가' 근거 표시 + 스윙 타점 확대"
  },
  {
   "dt": "2026-07-21",
   "target": "sentiment",
   "title": "시장 심리 지수 신설 — VIX·기간구조·MOVE 합성"
  }
 ]
}